{"latent_concepts": [{"name": "element", "values": ["0", "1", "2", "3", "4", "5", "6", "7", "8", "9"]}], "symbolic_concepts": [{"name": "target_member", "values": ["0", "1", "2", "3", "4", "5", "6", "7", "8", "9"]}], "target_concepts": [{"name": "member", "values": ["false", "true"]}], "raw_inputs": [{"name": "element_input(0)", "input_shape": [28, 28, 1], "latent_concept_name": "element"}, {"name": "element_input(1)", "input_shape": [28, 28, 1], "latent_concept_name": "element"}, {"name": "element_input(2)", "input_shape": [28, 28, 1], "latent_concept_name": "element"}], "symbolic_inputs": [{"name": "target_input", "symbolic_concept_name": "target_member", "num_values": 10}], "targets": [{"name": "member_output", "target_concept_name": "member", "multi_valued": false}], "concepts_to_learn": []}